beam/__init__.py
beam/cli.py
beam/clients/__init__.py
beam/clients/api.py
beam/clients/runner.py
beam/clients/syncthing/__init__.py
beam/clients/syncthing/client.py
beam/clients/syncthing/templates.py
beam/commands/__init__.py
beam/commands/down.py
beam/commands/init.py
beam/commands/start.py
beam/commands/up.py
beam/config.py
beam/constants.py
beam/decorators.py
beam/log.py
beam/processmanager.py
beam/telemetry.py
beam/util.py
beam_cli-0.1.0.dist-info/entry_points.txt
beam_cli-0.1.0.dist-info/WHEEL
beam_cli-0.1.0.dist-info/METADATA
beam_cli-0.1.0.dist-info/RECORD
