Metadata-Version: 2.1
Name: beam-cli
Version: 0.1.0
Summary: 
Author: Luke Lombardi
Author-email: luke@slai.io
Requires-Python: >=3.7,<4.0.0
Classifier: Programming Language :: Python :: 3
Classifier: Programming Language :: Python :: 3.7
Classifier: Programming Language :: Python :: 3.8
Classifier: Programming Language :: Python :: 3.9
Requires-Dist: python-syncthing-client (>=0.1.1,<0.2.0)
Requires-Dist: requests (>=2.28.1,<3.0.0)
Requires-Dist: rich (>=12.5.1,<13.0.0)
Requires-Dist: typer (>=0.6.1,<0.7.0)
Requires-Dist: websockets (>=10.3,<11.0)
Requires-Dist: yamldataclassconfig (>=1.5.0,<2.0.0)
